[{
    "district": "Khagaria",
    "block": "Allouli Beldaur",
    "link": "district/Khagaria/index.html",
    "new_confirmed": "9",
    "confirmed": "10",
    "active": "10",
    "recovered": "0",
    "deceased": "0",
    "color": ""
},
{
    "district": "Khagaria",
    "block": "Beldaur",
    "link": "district/Khagaria/index.html",
    "new_confirmed": "4",
    "confirmed": "4",
    "active": "4",
    "recovered": "0",
    "deceased": "0",
    "color": ""
},
{
    "district": "Khagaria",
    "block": "Chautham",
    "link": "district/Khagaria/index.html",
    "new_confirmed": "2",
    "confirmed": "11",
    "active": "11",
    "recovered": "0",
    "deceased": "0",
    "color": ""
},
{
    "district": "Khagaria",
    "block": "Gogari",
    "link": "district/Khagaria/index.html",
    "new_confirmed": "1",
    "confirmed": "1",
    "active": "1",
    "recovered": "0",
    "deceased": "0",
    "color": ""
},
{
    "district": "Khagaria",
    "block": "Khagaria",
    "link": "district/Khagaria/index.html",
    "new_confirmed": "0",
    "confirmed": "2",
    "active": "2",
    "recovered": "0",
    "deceased": "0",
    "color": ""
},
{
    "district": "Khagaria",
    "block": "Mansi",
    "link": "district/Khagaria/index.html",
    "new_confirmed": "0",
    "confirmed": "0",
    "active": "0",
    "recovered": "0",
    "deceased": "0",
    "color": ""
},
{
    "district": "Khagaria",
    "block": "Parbatta",
    "link": "district/Khagaria/index.html",
    "new_confirmed": "0",
    "confirmed": "0",
    "active": "0",
    "recovered": "0",
    "deceased": "0",
    "color": ""
},
{
    "district": "Khagaria",
    "block": "Unknown",
    "link": "district/Khagaria/index.html",
    "new_confirmed": "0",
    "confirmed": "0",
    "active": "0",
    "recovered": "0",
    "deceased": "0",
    "color": ""
},
{
    "district": "Khagaria",
    "block": "Total",
    "link": "district/Khagaria/index.html",
    "new_confirmed": "16",
    "confirmed": "28",
    "active": "28",
    "recovered": "0",
    "deceased": "0",
    "color": "orange"
}
]