[{
    "confirmed": "10", 
    "district": "Khagaria", 
    "color": "", 
    "link": "district/Khagaria/index.html", 
    "recovered": "0", 
    "active": "10", 
    "new_confirmed": "9", 
    "deceased": "0", 
    "block": "Allouli Beldaur"
},
{
    "confirmed": "4", 
    "district": "Khagaria", 
    "color": "", 
    "link": "district/Khagaria/index.html", 
    "recovered": "0", 
    "active": "4", 
    "new_confirmed": "4", 
    "deceased": "0", 
    "block": "Beldaur"
},
{
    "confirmed": "11", 
    "district": "Khagaria", 
    "color": "", 
    "link": "district/Khagaria/index.html", 
    "recovered": "0", 
    "active": "11", 
    "new_confirmed": "2", 
    "deceased": "0", 
    "block": "Chautham"
},
{
    "confirmed": "1", 
    "district": "Khagaria", 
    "color": "", 
    "link": "district/Khagaria/index.html", 
    "recovered": "0", 
    "active": "1", 
    "new_confirmed": "1", 
    "deceased": "0", 
    "block": "Gogari"
},
{
    "confirmed": "2", 
    "district": "Khagaria", 
    "color": "", 
    "link": "district/Khagaria/index.html", 
    "recovered": "0", 
    "active": "2", 
    "new_confirmed": "0", 
    "deceased": "0", 
    "block": "Khagaria"
},
{
    "confirmed": "0", 
    "district": "Khagaria", 
    "color": "", 
    "link": "district/Khagaria/index.html", 
    "recovered": "0", 
    "active": "0", 
    "new_confirmed": "0", 
    "deceased": "0", 
    "block": "Mansi"
},
{
    "confirmed": "0", 
    "district": "Khagaria", 
    "color": "", 
    "link": "district/Khagaria/index.html", 
    "recovered": "0", 
    "active": "0", 
    "new_confirmed": "0", 
    "deceased": "0", 
    "block": "Parbatta"
},
{
    "confirmed": "0", 
    "district": "Khagaria", 
    "color": "", 
    "link": "district/Khagaria/index.html", 
    "recovered": "0", 
    "active": "0", 
    "new_confirmed": "0", 
    "deceased": "0", 
    "block": "Unknown"
},
{
    "confirmed": "28", 
    "district": "Khagaria", 
    "color": "orange", 
    "link": "district/Khagaria/index.html", 
    "recovered": "0", 
    "active": "28", 
    "new_confirmed": "16", 
    "deceased": "0", 
    "block": "Total"
}
]