[{
    "confirmed": "5", 
    "district": "Saharsa", 
    "color": "", 
    "link": "district/Saharsa/index.html", 
    "recovered": "0", 
    "active": "5", 
    "new_confirmed": "5", 
    "deceased": "0", 
    "block": "KAHRA"
},
{
    "confirmed": "0", 
    "district": "Saharsa", 
    "color": "", 
    "link": "district/Saharsa/index.html", 
    "recovered": "0", 
    "active": "0", 
    "new_confirmed": "0", 
    "deceased": "0", 
    "block": "SATTAR KATIYA"
},
{
    "confirmed": "2", 
    "district": "Saharsa", 
    "color": "", 
    "link": "district/Saharsa/index.html", 
    "recovered": "0", 
    "active": "2", 
    "new_confirmed": "0", 
    "deceased": "0", 
    "block": "SAUR BAZAR"
},
{
    "confirmed": "0", 
    "district": "Saharsa", 
    "color": "", 
    "link": "district/Saharsa/index.html", 
    "recovered": "0", 
    "active": "0", 
    "new_confirmed": "0", 
    "deceased": "0", 
    "block": "PATARGHAT"
},
{
    "confirmed": "0", 
    "district": "Saharsa", 
    "color": "", 
    "link": "district/Saharsa/index.html", 
    "recovered": "0", 
    "active": "0", 
    "new_confirmed": "0", 
    "deceased": "0", 
    "block": "MAHISHI"
},
{
    "confirmed": "0", 
    "district": "Saharsa", 
    "color": "", 
    "link": "district/Saharsa/index.html", 
    "recovered": "0", 
    "active": "0", 
    "new_confirmed": "0", 
    "deceased": "0", 
    "block": "SONBARSA"
},
{
    "confirmed": "0", 
    "district": "Saharsa", 
    "color": "", 
    "link": "district/Saharsa/index.html", 
    "recovered": "0", 
    "active": "0", 
    "new_confirmed": "0", 
    "deceased": "0", 
    "block": "NAUHATTA"
},
{
    "confirmed": "0", 
    "district": "Saharsa", 
    "color": "", 
    "link": "district/Saharsa/index.html", 
    "recovered": "0", 
    "active": "0", 
    "new_confirmed": "0", 
    "deceased": "0", 
    "block": "SALKHUA"
},
{
    "confirmed": "0", 
    "district": "Saharsa", 
    "color": "", 
    "link": "district/Saharsa/index.html", 
    "recovered": "0", 
    "active": "0", 
    "new_confirmed": "0", 
    "deceased": "0", 
    "block": "BANMA ITAHRI"
},
{
    "confirmed": "1", 
    "district": "Saharsa", 
    "color": "", 
    "link": "district/Saharsa/index.html", 
    "recovered": "0", 
    "active": "1", 
    "new_confirmed": "1", 
    "deceased": "0", 
    "block": "SIMRI BAKHTIYARPUR"
},
{
    "confirmed": "1", 
    "district": "Saharsa", 
    "color": "", 
    "link": "district/Saharsa/index.html", 
    "recovered": "0", 
    "active": "1", 
    "new_confirmed": "1", 
    "deceased": "0", 
    "block": "Unknown"
},
{
    "confirmed": "9", 
    "district": "Saharsa", 
    "color": "orange", 
    "link": "district/Saharsa/index.html", 
    "recovered": "0", 
    "active": "9", 
    "new_confirmed": "7", 
    "deceased": "0", 
    "block": "Total"
}
]